searchxplorer/__init__.py
searchxplorer/search.py
searchxplorer-0.0.7.dist-info/METADATA
searchxplorer-0.0.7.dist-info/WHEEL
searchxplorer-0.0.7.dist-info/top_level.txt
searchxplorer-0.0.7.dist-info/RECORD
