Metadata-Version: 2.1
Name: searchxplorer
Version: 0.0.7
Summary: searchxplorer is a Python library that empowers developers with powerful search algorithms for efficient data exploration and retrieval.
Author: HD7(Harshit)
Author-email: <mail@HD7.com>
Keywords: search,exploration,Python library,data retrieval,search algorithms,linear search,binary search,data exploration,data navigation,data analysis,data retrieval,data search,search utility,data exploration library,efficient search,Python development,Python programming,developer tools,open-source,code library
Classifier: Development Status :: 1 - Planning
Classifier: Intended Audience :: Developers
Classifier: Programming Language :: Python :: 3
Classifier: Operating System :: Unix
Classifier: Operating System :: MacOS :: MacOS X
Classifier: Operating System :: Microsoft :: Windows
